{
  "recentFiles": [
    {
      "basename": "interview_prep",
      "path": "Second Brain/interview_prep.md"
    },
    {
      "basename": "lastMinNotes",
      "path": "Second Brain/DSA/lastMinNotes.md"
    },
    {
      "basename": "game_of_life.md",
      "path": "Second Brain/ProjectBLlog/game_of_life.md.md"
    },
    {
      "basename": "242. Valid Anagram",
      "path": "Second Brain/DSA/Problems/242. Valid Anagram.md"
    },
    {
      "basename": "Intro",
      "path": "Second Brain/SQL/Intro.md"
    },
    {
      "basename": "Untitled",
      "path": "Second Brain/Aptitude/Untitled.md"
    },
    {
      "basename": "Fibonacci Series",
      "path": "Second Brain/DSA/Problems/Fibonacci Series.md"
    },
    {
      "basename": "Untitled",
      "path": "Second Brain/SQL/Untitled.md"
    },
    {
      "basename": "recusrion1",
      "path": "Second Brain/DSA/Recursion/recusrion1.md"
    },
    {
      "basename": "69. Unique Paths",
      "path": "Second Brain/DSA/Problems/69. Unique Paths.md"
    },
    {
      "basename": "Day Planner-20220715",
      "path": "Day Planners/Day Planner-20220715.md"
    },
    {
      "basename": "README",
      "path": "README.md"
    },
    {
      "basename": "trueRandomNumberGenerator.md",
      "path": "Second Brain/ProjectBLlog/trueRandomNumberGenerator.md.md"
    },
    {
      "basename": "random_number.md",
      "path": "Second Brain/ProjectBLlog/random_number.md.md"
    }
  ],
  "omittedPaths": [],
  "maxLength": null
}